LICENSE
MANIFEST.in
README.rst
posthaste.py
setup.py
posthaste.egg-info/PKG-INFO
posthaste.egg-info/SOURCES.txt
posthaste.egg-info/dependency_links.txt
posthaste.egg-info/entry_points.txt
posthaste.egg-info/requires.txt
posthaste.egg-info/top_level.txt