Metadata-Version: 1.0
Name: posthaste
Version: 0.2.2
Summary: Gevent-based, multithreaded tool for interacting with OpenStack Swift and Rackspace Cloud Files
Home-page: https://github.com/rackerlabs/posthaste
Author: Matt Martz
Author-email: matt@sivel.net
License: Apache License, Version 2.0
Keywords: rackspace openstack cloud cloudfiles swift
Platform: UNKNOWN
Classifier: Programming Language :: Python
Classifier: Environment :: Console
Classifier: License :: OSI Approved :: Apache Software License
Classifier: Operating System :: OS Independent
